dvh_tools/__init__.py
dvh_tools/bq_to_oracle/README.md
dvh_tools/bq_to_oracle/__init__.py
dvh_tools/bq_to_oracle/bq_reader.py
dvh_tools/bq_to_oracle/data_transfer.py
dvh_tools/bq_to_oracle/oracle_writer.py
dvh_tools/bq_to_oracle/test_oracle_writer.py
dvh_tools/cloud_functions.py
dvh_tools/dbt_tools/__init__.py
dvh_tools/dbt_tools/dbt_docs_publish.py
dvh_tools/dbt_tools/dbt_run_airflow.py
dvh_tools/dbt_tools/environment_lokal_user.sh
dvh_tools/dbt_tools/generate_comments_from_sql.py
dvh_tools/dbt_tools/generate_comments_utils.py
dvh_tools/dbt_tools/get_comments_from_oracle.py
dvh_tools/dbt_tools/readme
dvh_tools/find_project_root.py
dvh_tools/oracle.py
dvh_tools-0.12.3.dist-info/METADATA
dvh_tools-0.12.3.dist-info/WHEEL
dvh_tools-0.12.3.dist-info/licenses/LICENSE
dvh_tools-0.12.3.dist-info/RECORD
