Metadata-Version: 2.4
Name: dvh-tools
Version: 0.12.3
Summary: 
License: MIT
License-File: LICENSE
Author: NAV
Requires-Python: >=3.12,<4.0
Classifier: License :: OSI Approved :: MIT License
Classifier: Programming Language :: Python :: 3
Classifier: Programming Language :: Python :: 3.12
Classifier: Programming Language :: Python :: 3.13
Classifier: Programming Language :: Python :: 3.14
Requires-Dist: google-cloud-bigquery (>=3.35.1,<4.0.0)
Requires-Dist: google-cloud-secret-manager (>=2.24.0,<3.0.0)
Requires-Dist: google-cloud-storage (>=3.2.0,<4.0.0)
Requires-Dist: loguru (>=0.7.3,<0.8.0)
Requires-Dist: oracledb (>=3.0.0,<4)
Requires-Dist: pandas (>=2.3.1,<3.0.0)
Requires-Dist: toml (>=0.10.2,<0.11.0)
Project-URL: Repository, https://github.com/navikt/dvh-tools
